HeifImagePlugin.py
heif_image_plugin-0.7.0.dist-info/LICENSE
heif_image_plugin-0.7.0.dist-info/METADATA
heif_image_plugin-0.7.0.dist-info/WHEEL
heif_image_plugin-0.7.0.dist-info/top_level.txt
heif_image_plugin-0.7.0.dist-info/RECORD
