Metadata-Version: 2.1
Name: heif-image-plugin
Version: 0.7.0
Summary: Simple HEIF/HEIC images plugin for Pillow base on pyhief library.
Home-page: https://github.com/uploadcare/heif-image-plugin
Download-URL: https://github.com/uploadcare/heif-image-plugin/archive/v0.7.0.tar.gz
Author: Alexander Karpinsky
Author-email: homm86@gmail.com
License: MIT
Keywords: heif,heic,Pillow,plugin,pyhief
Classifier: License :: OSI Approved :: MIT License
Classifier: Natural Language :: English
Classifier: Operating System :: MacOS :: MacOS X
Classifier: Operating System :: POSIX :: Linux
Classifier: Programming Language :: Python :: 3
Classifier: Programming Language :: Python :: 3.7
Classifier: Programming Language :: Python :: 3.8
Classifier: Programming Language :: Python :: 3.9
Classifier: Programming Language :: Python :: 3.10
Classifier: Programming Language :: Python :: Implementation :: PyPy
Classifier: Topic :: Multimedia :: Graphics
License-File: LICENSE
Requires-Dist: pyheif>=0.8.0
Requires-Dist: piexif>=1.1.3
Provides-Extra: test
Requires-Dist: pillow>=9.0.0; extra == "test"
Requires-Dist: pytest>=8.3.2; extra == "test"
Requires-Dist: pytest-cov>=5.0.0; extra == "test"
